Metadata-Version: 2.1
Name: devconfig
Version: 0.4.6
Summary: Configuration handling for developers
Home-page: https://denz1.gitlab.io/devconfig
Author: Denis Mishchishin
Author-email: dennz78@gmail.com
License: MIT
Platform: UNKNOWN
Classifier: Development Status :: 3 - Alpha
Classifier: Environment :: Console
Classifier: License :: OSI Approved :: MIT License
Classifier: Intended Audience :: Developers
Classifier: Intended Audience :: Information Technology
Classifier: Natural Language :: English
Classifier: Operating System :: POSIX :: Linux
Classifier: Programming Language :: Python :: 3
Classifier: Programming Language :: Python :: 3.7
Classifier: Topic :: Utilities
